csspring/__init__.py
csspring/py.typed
csspring/selectors.py
csspring/utils.py
csspring/values.py
csspring/syntax/__init__.py
csspring/syntax/grammar.py
csspring/syntax/parsing.py
csspring/syntax/preprocessing.py
csspring/syntax/tokenizing.py
csspring-2.0.5.dist-info/licenses/LICENSE.txt
csspring-2.0.5.dist-info/METADATA
csspring-2.0.5.dist-info/WHEEL
csspring-2.0.5.dist-info/top_level.txt
csspring-2.0.5.dist-info/RECORD
