Metadata-Version: 2.4
Name: csspring
Version: 2.0.5
Summary: A CSS parsing library
Author-email: Armen Michaeli <armen@armen.michaeli.name>
License-Expression: GPL-3.0-only
Project-URL: Github, http://github.com/amn/csspring
Classifier: Development Status :: 5 - Production/Stable
Classifier: Environment :: Console
Classifier: Intended Audience :: Developers
Classifier: Operating System :: POSIX
Classifier: Programming Language :: Python :: 3
Classifier: Topic :: Software Development :: Libraries
Classifier: Topic :: Text Processing
Requires-Python: >=3.11
License-File: LICENSE.txt
Provides-Extra: tests
Requires-Dist: mypy>=1.7.0; extra == "tests"
Requires-Dist: pytest>=6.2.4; extra == "tests"
Dynamic: license-file
